.DS_Store
mogp/__init__.py
mogp/allocmodel.py
mogp/mogp_constrained.py
mogp/neg_linear.py
mogp/obsmodel.py
mogp/test_package.py
mogp/utils.py
mogp-1.0.0.dist-info/LICENSE
mogp-1.0.0.dist-info/METADATA
mogp-1.0.0.dist-info/WHEEL
mogp-1.0.0.dist-info/top_level.txt
mogp-1.0.0.dist-info/RECORD
