Metadata-Version: 2.1
Name: mogp
Version: 1.0.0
Summary: Mixture of Gaussian Processes Model for Sparse Longitudinal Data
Home-page: https://github.com/fraenkel-lab/mogp
Author: Divya Ramamoorthy
Author-email: divyar@mit.edu
License: MIT
Requires-Python: >=3.8
License-File: LICENSE
Requires-Dist: numpy (<1.24,>=1.20)
Requires-Dist: GPy (==1.10)
Requires-Dist: scikit-learn
Requires-Dist: matplotlib
Requires-Dist: pytest
